GameStorageAPI/DataTypes.py
GameStorageAPI/__init__.py
GameStorageAPI/game.py
GameStorageAPI/storage.py
GameStorageAPI-1.1.20.dist-info/LICENSE
GameStorageAPI-1.1.20.dist-info/METADATA
GameStorageAPI-1.1.20.dist-info/WHEEL
GameStorageAPI-1.1.20.dist-info/top_level.txt
GameStorageAPI-1.1.20.dist-info/RECORD
